[
  {
    "id": "dcb44ec4-291b-43ab-9780-7be72754e33e",
    "data": [
      {
        "text": "I\u0027m really excited",
        "userDefined": false
      }
    ],
    "isTemplate": false,
    "count": 0,
    "updated": 0
  },
  {
    "id": "5ad8c5b4-8517-4ab7-a92f-fcb7ae0cf42e",
    "data": [
      {
        "text": "I\u0027m excited to start our friendship",
        "userDefined": false
      }
    ],
    "isTemplate": false,
    "count": 0,
    "updated": 0
  },
  {
    "id": "9a909ebe-5bba-4c91-9514-38b1cc197c9d",
    "data": [
      {
        "text": "I am excited",
        "userDefined": false
      }
    ],
    "isTemplate": false,
    "count": 0,
    "updated": 0
  },
  {
    "id": "c8f540f2-2646-4d56-bd1b-508d8a80706a",
    "data": [
      {
        "text": "how excited I am",
        "userDefined": false
      }
    ],
    "isTemplate": false,
    "count": 0,
    "updated": 0
  },
  {
    "id": "8db1dc98-531e-4c40-8687-059516fd23ba",
    "data": [
      {
        "text": "I\u0027m excited about working with you",
        "userDefined": false
      }
    ],
    "isTemplate": false,
    "count": 0,
    "updated": 0
  },
  {
    "id": "6a80a4c0-b738-467d-8fca-c482131f739a",
    "data": [
      {
        "text": "I\u0027m thrilled",
        "userDefined": false
      }
    ],
    "isTemplate": false,
    "count": 0,
    "updated": 0
  }
]