[
  {
    "id": "f35c0420-c3ec-43ef-a5d5-a99300ff1c63",
    "data": [
      {
        "text": "I\u0027m happy to see you",
        "userDefined": false
      }
    ],
    "isTemplate": false,
    "count": 0,
    "updated": 0
  },
  {
    "id": "635148cc-b0ed-46f5-b318-00c9a49d7d74",
    "data": [
      {
        "text": "I\u0027m ",
        "userDefined": false
      },
      {
        "text": "happy",
        "meta": "@sys.ignore",
        "userDefined": false
      },
      {
        "text": " to see you",
        "userDefined": false
      }
    ],
    "isTemplate": false,
    "count": 0,
    "updated": 0
  },
  {
    "id": "de00bc65-26e1-444d-b8ad-892350184fb0",
    "data": [
      {
        "text": "happy",
        "meta": "@sys.ignore",
        "userDefined": false
      }
    ],
    "isTemplate": false,
    "count": 0,
    "updated": 0
  },
  {
    "id": "7f1c31ad-77fb-4f0c-97e7-2be67645e69c",
    "data": [
      {
        "text": "if you\u0027re ",
        "userDefined": false
      },
      {
        "text": "happy",
        "meta": "@sys.ignore",
        "userDefined": false
      },
      {
        "text": " then I\u0027m ",
        "userDefined": false
      },
      {
        "text": "happy",
        "meta": "@sys.ignore",
        "userDefined": false
      }
    ],
    "isTemplate": false,
    "count": 0,
    "updated": 0
  },
  {
    "id": "d338c20d-d783-462d-9671-ad3d5114407f",
    "data": [
      {
        "text": "I\u0027m happy to help",
        "userDefined": false
      }
    ],
    "isTemplate": false,
    "count": 0,
    "updated": 0
  },
  {
    "id": "60ec7bd2-174a-4f71-a672-7ba91bd9b251",
    "data": [
      {
        "text": "I\u0027m ",
        "userDefined": false
      },
      {
        "text": "happy",
        "meta": "@sys.ignore",
        "userDefined": false
      },
      {
        "text": " for you",
        "userDefined": false
      }
    ],
    "isTemplate": false,
    "count": 0,
    "updated": 0
  },
  {
    "id": "d4556fc9-5fb8-4420-8c74-bf2fe84f19bb",
    "data": [
      {
        "text": "I am ",
        "userDefined": false
      },
      {
        "text": "happy",
        "meta": "@sys.ignore",
        "userDefined": false
      }
    ],
    "isTemplate": false,
    "count": 0,
    "updated": 0
  }
]